{
  "bookId": "exo",
  "chapters": {
    "1": {},
    "2": {},
    "3": {
      "14": [
        {
          "ref": "jhn.8.58",
          "reason": "Antes de Abraão, EU SOU"
        },
        {
          "ref": "rev.1.8",
          "reason": "O que é, era e há de vir"
        },
        {
          "ref": "isa.43.11",
          "reason": "Eu sou o Senhor"
        }
      ]
    },
    "4": {},
    "5": {},
    "6": {},
    "7": {},
    "8": {},
    "9": {},
    "10": {},
    "11": {},
    "12": {
      "46": [
        {
          "ref": "jhn.19.36",
          "reason": "Nenhum osso será quebrado"
        },
        {
          "ref": "psa.34.20",
          "reason": "Ele guarda todos os seus ossos"
        }
      ]
    },
    "13": {},
    "14": {},
    "15": {},
    "16": {},
    "17": {},
    "18": {},
    "19": {},
    "20": {
      "1": [
        {
          "ref": "deu.5.6",
          "reason": "Os Dez Mandamentos"
        },
        {
          "ref": "mat.19.18",
          "reason": "Jesus cita os mandamentos"
        }
      ]
    },
    "21": {},
    "22": {},
    "23": {},
    "24": {},
    "25": {},
    "26": {},
    "27": {},
    "28": {},
    "29": {},
    "30": {},
    "31": {},
    "32": {},
    "33": {},
    "34": {},
    "35": {},
    "36": {},
    "37": {},
    "38": {},
    "39": {},
    "40": {}
  }
}